tests/test_fields.py
tests/test_dbpreferences.py
tests/test_old_API.py
tests/test_doctest.py
tests/test_data_eval.py
tests/__init__.py
tests/utils/__init__.py
tests/utils/BrowserDebug.py
dbpreferences/admin.py
dbpreferences/fields.py
dbpreferences/models.py
dbpreferences/forms.py
dbpreferences/__init__.py
dbpreferences/middleware.py
dbpreferences/templates/dbpreferences/model_admin_edit_link.html
dbpreferences/templates/dbpreferences/edit_form.html
dbpreferences/tools/easy_import.py
dbpreferences/tools/data_eval.py
dbpreferences/tools/__init__.py
dbpreferences/tools/forms_utils.py
test_project/preference_forms.py
test_project/urls.py
test_project/models.py
test_project/__init__.py
test_project/settings.py
test_project/views.py
django_dbpreferences-0.6.0.dist-info/DESCRIPTION.rst
django_dbpreferences-0.6.0.dist-info/RECORD
django_dbpreferences-0.6.0.dist-info/top_level.txt
django_dbpreferences-0.6.0.dist-info/METADATA
django_dbpreferences-0.6.0.dist-info/WHEEL
django_dbpreferences-0.6.0.dist-info/metadata.json
