Metadata-Version: 2.0
Name: django-dbpreferences
Version: 0.6.0
Summary: With django-dbpreferences you can store app/user settings into the database.
Home-page: http://code.google.com/p/django-dbpreferences/
Author: Jens Diemer
Author-email: django-dbpreferences@jensdiemer.de
License: UNKNOWN
Platform: UNKNOWN
Classifier: Development Status :: 5 - Production/Stable
Classifier: Environment :: Web Environment
Classifier: Intended Audience :: Developers
Classifier: License :: OSI Approved :: GNU General Public License (GPL)
Classifier: Programming Language :: Python
Classifier: Framework :: Django
Classifier: Topic :: Database :: Front-Ends
Classifier: Topic :: Documentation
Classifier: Topic :: Internet :: WWW/HTTP :: Dynamic Content
Classifier: Topic :: Internet :: WWW/HTTP :: Site Management
Classifier: Topic :: Internet :: WWW/HTTP :: WSGI :: Application
Classifier: Operating System :: OS Independent
Requires-Dist: Django
Requires-Dist: django-tools
